{
  "users": [
    {
      "username": "testuser1",
      "email": "test1@example.com",
      "mobile": "1234567890",
      "password": "Password123!",
      "id": "d616"
    },
    {
      "username": "testuser2",
      "email": "test2@example.com",
      "mobile": "0987654321",
      "password": "Password123!",
      "id": "3808"
    },
    {
      "id": "b07e",
      "username": "asw",
      "email": "aswin@123",
      "mobile": "9952366919",
      "password": "asw@321"
    },
    {
      "id": "e97b",
      "username": "asw",
      "password": "asw@321"
    },
    {
      "id": "f99b",
      "username": "asw",
      "password": "asw@321"
    },
    {
      "id": "2561",
      "username": "asw",
      "password": "asw@321"
    },
    {
      "id": "c94d",
      "username": "asw",
      "password": "asw@321"
    },
    {
      "id": "1d91",
      "username": "asw",
      "password": "asw@321"
    },
    {
      "id": "7adf",
      "username": "asw",
      "password": "asw@321"
    },
    {
      "id": "d7a2",
      "username": "asw",
      "password": "asw@321"
    },
    {
      "id": "1105",
      "username": "asw",
      "password": "asw@321"
    },
    {
      "id": "cd72",
      "username": "asw",
      "password": "asw@321"
    },
    {
      "id": "39a8",
      "username": "asw",
      "password": "asw@321"
    },
    {
      "id": "0ffb",
      "username": "asw",
      "password": "asw@321"
    },
    {
      "id": "d344",
      "username": "asw",
      "password": "asw@321"
    },
    {
      "id": "d5d9",
      "username": "asw",
      "password": "asw@321"
    },
    {
      "id": "3034",
      "username": "asw",
      "password": "asw@321"
    },
    {
      "id": "b228",
      "username": "asw",
      "password": "asw@321"
    },
    {
      "id": "d272",
      "username": "asw",
      "password": "asw@321"
    },
    {
      "id": "853c",
      "username": "asw",
      "password": "asw@321"
    },
    {
      "id": "7f2d",
      "username": "asw",
      "password": "asw@321"
    },
    {
      "id": "8fdd",
      "username": "asw",
      "password": "asw@321"
    },
    {
      "id": "9ac9",
      "username": "asw",
      "password": "asw@321"
    },
    {
      "id": "c9a1",
      "username": "asw",
      "password": "asw@321"
    },
    {
      "id": "5508",
      "username": "asw",
      "password": "asw@321"
    },
    {
      "id": "8f5b",
      "username": "asw",
      "password": "asw@321"
    },
    {
      "id": "f656",
      "username": "asw",
      "password": "asw@321"
    },
    {
      "id": "6fb5",
      "username": "asw",
      "email": "asw@123",
      "mobile": "9952366919",
      "password": "asw#321"
    },
    {
      "id": "3910",
      "username": "asw",
      "password": "asw#321"
    },
    {
      "id": "c232",
      "username": "asw",
      "password": "asw#321"
    },
    {
      "id": "f4e8",
      "username": "asw",
      "password": "asw#321"
    },
    {
      "id": "4ef1",
      "username": "asw",
      "email": "asw@123",
      "mobile": "9952366919",
      "password": "asw#123"
    },
    {
      "id": "75d2",
      "username": "asw",
      "password": "asw#123"
    },
    {
      "id": "f01d",
      "username": "asw",
      "password": "asw#123"
    },
    {
      "id": "28ac",
      "username": "",
      "password": "caes123@"
    },
    {
      "id": "c899",
      "username": "",
      "password": "caes123@"
    },
    {
      "id": "4859",
      "username": "",
      "password": "caes123@"
    },
    {
      "id": "08bd",
      "username": "",
      "password": "var#123"
    },
    {
      "id": "d3d1",
      "username": "",
      "password": "varsf@123"
    },
    {
      "id": "e9ae",
      "username": "",
      "password": "var@123"
    },
    {
      "id": "c0db",
      "username": "",
      "password": "adad123@"
    },
    {
      "id": "3b28",
      "username": "",
      "password": "adad123@"
    },
    {
      "id": "f58a",
      "username": "",
      "password": "adad123@"
    },
    {
      "id": "3d57",
      "username": "",
      "password": "adad123@"
    },
    {
      "id": "c11f",
      "username": "",
      "password": "adad123@"
    },
    {
      "id": "5d4b",
      "username": "",
      "password": "adad123@"
    },
    {
      "id": "639a",
      "username": "",
      "password": "adad123@"
    },
    {
      "id": "903d",
      "username": "",
      "password": "adad123@"
    },
    {
      "id": "acf6",
      "username": "",
      "password": "adad123@"
    },
    {
      "id": "0a45",
      "username": "",
      "password": "nxm#12"
    },
    {
      "id": "b869",
      "username": "",
      "password": "bss#123"
    },
    {
      "id": "6330",
      "username": "",
      "password": "carsf#123"
    },
    {
      "id": "c97f",
      "username": "aswin",
      "email": "aswin@123",
      "mobile": "9952366919",
      "password": "var#123"
    },
    {
      "id": "71d7",
      "username": "aswin",
      "password": "var#123"
    },
    {
      "id": "f65b",
      "username": "aswin",
      "email": "ravu@123",
      "mobile": "9952366919",
      "password": "Saawe@123"
    },
    {
      "id": "f356",
      "username": "aswin",
      "password": "Saawe@123"
    },
    {
      "id": "435b",
      "username": "",
      "password": "sgshs#123"
    },
    {
      "id": "367f",
      "username": "",
      "password": "dzfd#12"
    },
    {
      "id": "edf5",
      "username": "",
      "password": "svvs#123"
    },
    {
      "id": "f401",
      "username": "adffa",
      "email": "ravi@23",
      "mobile": "9952366919",
      "password": "fsts#123"
    },
    {
      "id": "128a",
      "username": "adffa",
      "password": "fsts#123"
    },
    {
      "id": "4054",
      "username": "aswin",
      "email": "aswin@123",
      "mobile": "9952366919",
      "password": "sdgs#123"
    },
    {
      "id": "1639",
      "username": "aswin",
      "password": "sdgs#123"
    }
  ]
}